[
  {
    "name": "蔡銘修",
    "email": "mhtsai@ntut.edu.tw",
    "latestUpdate": "2025-09-24 13:22:36",
    "objective": "中文概述：專題報告、專題演講、研究小組討論。\nCase study. Seminar. Group meeting.",
    "schedule": "01 09/10 重要所務說明及課程概述\n02 09/17 技職所論文撰寫規範說明\n03 09/24 1. 摘要、緒論。2. 研究目的與待答問題、研究範圍、名詞釋義。\n04 10/01 3. 文獻探討。4. 參考文獻 (APA)。5. 問卷調查法、實驗法與行動研究。\n05 10/08 6. 研究架構、研究步驟。7. 研究對象、研究工具、研究場域。\n06 10/15 論文計畫第一次報告 (5 人)。\n07 10/22 第一次專題演講 (技職教育組)\n08 10/29 論文計畫第一次報告 (5 人)。\n09 11/05 期中考週\n10 11/12 9. 研究倫理。10. 論文計畫口試前應注意之事項\n11 11/19 論文計畫口試模擬演練 1 (2 人報告)\n12 11/26 論文計畫口試模擬演練 1 (2 人報告)\n13 12/03 論文計畫口試模擬演練 2 (2 人報告)\n14 12/10 論文計畫口試模擬演練 3 (2 人報告)\n15 12/17 第二次專題演講 (人力資源組)\n16 12/24 論文計畫口試模擬演練 5 (2 人報告)\n17 12/31 口試相關注意事項\n18 01/08 期末考週",
    "scorePolicy": "1. 出席 10%(無故缺課扣 5 分 / 次，請假兩次以上第二次起扣 2 分 / 次）\n2. 課堂參與度 20%\n3. 論文計畫第一次報告 20%\n4. 論文計畫口試模擬演練 (報告者) 25%\n5. 論文計畫口試模擬演練 (口試者) 15%",
    "materials": "1.【在開始... 之前應注意的 X 件事，... 一定不能做的 X 件事系列】，每組報告不得超過 30 分鐘。\n2. 論文計畫模擬演練 (前三章)- 共 6 週，每週排定 3 位發表人及 3 位模擬口委，每位 20-30 分鐘，本學期每人至少負責報告及擔任評論 1 次。",
    "consultation": "email 給授課教師: mhtsai@ntut.edu.tw 或者 另約線上 meeting 時間",
    "課程對應SDGs指標": "SDG4：優質教育（Quality Education）",
    "課程是否導入AI": "● 使用生成式 AI 作為教學過程的輔助工具（Use generative AI tools as an aid to the teaching process）● 鼓勵學生使用生成式 AI 工具（Encourage students to use generative AI tools）",
    "remarks": "",
    "foreignLanguageTextbooks": false
  }
]
