[
  {
    "name": "柯明村",
    "email": "mtke@ntut.edu.tw",
    "latestUpdate": "2025-09-12 22:42:49",
    "objective": "因應全球淨零碳排趨勢，能源管理與碳管理為國家各產業提升競爭力的重要環節。本課程將從 ISO50001 能源管理與 ISO14064 碳管理制度出發，講授能源管理、能源績效評估、碳管理、和績效提升 / 減碳計算之量測與驗證方法學。講授內容涵蓋：關鍵觀念、節能 / 減碳技術、績效 / 減碳量測與驗證方法、節能 / 減碳統計分析方法學、和案例 EXCEL 操作與討論。\nIn response to the global trend of net-zero carbon emissions, energy management and carbon management are important links in improving the competitiveness of various industries in the country. This course will start from the ISO50001 energy management and ISO14064 carbon management systems and teach the measurement and verification methodologies of energy management, energy performance assessment, carbon management, and performance improvement/carbon reduction calculations. The teaching contents cover: key concepts, energy saving/carbon reduction technology, performance/carbon reduction measurement and verification methods, energy saving/carbon reduction statistical analysis methodology, and EXCEL case practice and discussion.",
    "schedule": "(1) 課程簡介與 ISO 50001 能源管理 / ISO 14064 碳管理簡介\n(2) 能源績效量測與驗證 - 關鍵與基礎：ISO 50001 能源管理系統、國際能源績效量測與驗證協定 (International Performance Measurement and Verification Protocol, IPMVP)\n(3) 能源績效量測與驗證 - 重要議題：IPMVP 重要內涵、選項與簡單案例\n(4) 能源績效量測與驗證 - 量測：量測儀表、量測方法\n(5) 能源績效量測與驗證 - 量測與取樣：誤差與不確定度、取樣分析\n(6) 能源績效量測與驗證 - 計算：統計分析 I 與 EXCEL 應用實作\n(7) 能源績效量測與驗證 - 計算：統計分析 II - 數據判定、不確定度分析與 EXCEL 應用實作\n(8) 能源績效量測與驗證 - 計算：數據判定、組合不確定度與 EXCEL 應用實作\n(9) 能源績效量測與驗證 - 計算：案例操作與 EXCEL 應用實作\n(10) 碳盤查與管理 IOS14064：IOS 14064 系列標準內涵\n(11) 碳盤查關鍵項目：各範疇 (Scope) 鑑別與說明\n(12) 節能 / 減碳技術應用：系統節能技術、減碳技術\n(13)\t能源管理與碳管理：組織 (Organization) 管理、能源資通訊技術 (Energy Information and Communication Technology, EICT) 應用\n(14)\t實務案例討論：生產性質行業\n(15)\t實務案例討論：非生產性質行業\n(16)\t期末報告 (簡報) I\n(17)\t期末報告 (簡報) II\n(18)\t期末考 (Open book)",
    "scorePolicy": "作業 20%\n期末書面報告 30%\n期末簡報 30%\n期末考 20%",
    "materials": "教師講義模組、ISO 文獻資料",
    "consultation": "研究室分機號碼：3509 研究室位置：綜合科館 515-1 室 Office hours: 週四 15:30 ~ 16:30、週五 14:30 ~ 18:00",
    "課程對應SDGs指標": "SDG11：永續城市與社區（Sustainable Cities and Communities）SDG13：氣候行動（Climate Action）",
    "課程是否導入AI": "● 使用生成式 AI 進行課堂即時互動（Use generative AI for real-time classroom interaction）",
    "remarks": "如學校因應疫情而實施遠距離教學，本課程將全採遠距授課，並將使用 teams 來進行遠距授課。",
    "foreignLanguageTextbooks": false
  }
]
